[
  {
    "emoji": "🔌",
    "title": "Data Source Integrations Platform",
    "problem": "ProspectPro needs a standardized way to add and manage multiple data providers while tracking per-call costs.",
    "solution": "Factory pattern with provider modules (Hunter, Apollo, Google), cost tracking, rate limiting, and circuit breakers. FINRA as premium provider.",
    "acceptance": [
      "DataSource interface and factory implemented",
      "Providers: Hunter, Apollo, Google complete",
      "Cost tracking with Supabase logs",
      "Rate limiting and circuit breakers in place",
      "FINRA provider subtask with OAuth and endpoints",
      "Tests and documentation added"
    ],
    "impact": "Faster integrations, lower per-lead costs, enables FINRA premium tier.",
    "requirements": [
      "TypeScript interfaces under lib/integrations",
      "Supabase tables for cost and usage logs",
      "Reusable error handling and retry logic"
    ],
    "priority": "High",
    "phase": "Q1 2026",
    "points": 21,
    "labels": ["data-integration"],
    "addToProject": true
  },
  {
    "emoji": "💰",
    "title": "Stripe Usage-Based Billing Implementation",
    "problem": "Current pricing is unprofitable versus actual costs.",
    "solution": "Stripe usage meters and tiered pricing with real-time tracking, customer portal integration, and migration strategy.",
    "acceptance": [
      "Usage meter prospectpro_lead_processed created",
      "Products and prices for Starter, Pro, Enterprise tiers",
      "Webhooks for invoice and usage events registered",
      "Usage tracking middleware deployed",
      "Customer portal integration enabled",
      "Migration plan for existing customers",
      "Tests and documentation completed"
    ],
    "impact": "70%+ gross margin and accurate usage-based billing with lower support overhead.",
    "requirements": [
      "lib/stripe/usage-billing.ts implementation",
      "lib/stripe/webhooks.ts handlers",
      "middleware/usage-tracker.ts instrumentation",
      "Supabase storage for usage logs"
    ],
    "priority": "High",
    "phase": "Q4 2025",
    "points": 13,
    "labels": ["billing"],
    "addToProject": true
  },
  {
    "emoji": "📊",
    "title": "Cost Monitoring & Budget Controls",
    "problem": "No real-time cost monitoring exists, creating risk of budget overruns.",
    "solution": "Build API cost tracking, budget allocations, alerts, circuit breakers, and admin dashboards.",
    "acceptance": [
      "Supabase tables api_usage_logs and budget_allocations in place",
      "Cost logger integrated across providers",
      "Budget alerts and circuit breaker logic active",
      "Admin dashboards available",
      "Tests and documentation updated"
    ],
    "impact": "Cost visibility with enforced budget protection across tiers.",
    "requirements": ["Edge Function logging hooks", "RLS-safe reporting views"],
    "priority": "High",
    "phase": "Q4 2025",
    "points": 8,
    "labels": ["cost-monitoring"],
    "addToProject": true
  },
  {
    "emoji": "💵",
    "title": "Pricing Strategy Implementation",
    "problem": "Base and Professional tiers remain loss-making at low volumes.",
    "solution": "Adopt usage-based tiers (Starter, Pro, Enterprise, Financial Services) with gating and migration plan.",
    "acceptance": [
      "Pricing configuration file created",
      "Tier gating middleware enforcing limits",
      "Migration plan and communications drafted",
      "Tests and documentation complete"
    ],
    "impact": "Sustainable unit economics across all tiers with transparent billing.",
    "requirements": [
      "Config-driven tier rules",
      "Edge Function enforcement and audit logs"
    ],
    "priority": "Medium",
    "phase": "Q4 2025",
    "points": 5,
    "labels": ["pricing"],
    "addToProject": true
  }
]
